signature_roster_reconciliation/__init__.py
signature_roster_reconciliation/cli.py
signature_roster_reconciliation-1.0.0.dist-info/METADATA
signature_roster_reconciliation-1.0.0.dist-info/WHEEL
signature_roster_reconciliation-1.0.0.dist-info/entry_points.txt
signature_roster_reconciliation-1.0.0.dist-info/top_level.txt
signature_roster_reconciliation-1.0.0.dist-info/RECORD
