Metadata-Version: 2.4
Name: signature-roster-reconciliation
Version: 1.0.0
Summary: Roster vs Orders reconciliation tool for Signature Locker
Author-email: Signature Athletics <ap13@signaturelocker.com>
License: MIT
Project-URL: Homepage, https://github.com/ap13-signature-tools/signature-roster-reconciliation
Keywords: roster,reconciliation,signature,locker,orders
Classifier: Development Status :: 5 - Production/Stable
Classifier: Intended Audience :: End Users/Desktop
Classifier: License :: OSI Approved :: MIT License
Classifier: Programming Language :: Python :: 3
Classifier: Programming Language :: Python :: 3.8
Classifier: Programming Language :: Python :: 3.9
Classifier: Programming Language :: Python :: 3.10
Classifier: Programming Language :: Python :: 3.11
Classifier: Programming Language :: Python :: 3.12
Requires-Python: >=3.8
Requires-Dist: pandas>=1.3.0
Requires-Dist: openpyxl>=3.0.0
Requires-Dist: numpy>=1.20.0
